footnotes2biblio/__init__.py
footnotes2biblio/__main__.py
footnotes2biblio/footnote.py
footnotes2biblio/parsers.py
footnotes2biblio-0.0.2a0.dist-info/LICENSE
footnotes2biblio-0.0.2a0.dist-info/METADATA
footnotes2biblio-0.0.2a0.dist-info/WHEEL
footnotes2biblio-0.0.2a0.dist-info/entry_points.txt
footnotes2biblio-0.0.2a0.dist-info/top_level.txt
footnotes2biblio-0.0.2a0.dist-info/RECORD
