Metadata-Version: 2.1
Name: footnotes2biblio
Version: 0.0.2a0
Summary: "A Python tool that scrapes your footnotes in any Word doc and builds a bibliography so you don't have to"
Home-page: https://github.com/ACour008/footnotes2biblio
Author: ACOUR008
Author-email: acour008@fastmail.com
License: UNKNOWN
Project-URL: Bug Tracker, https://github.com/ACour008/footnotes2biblio/issues
Platform: UNKNOWN
Classifier: Programming Language :: Python :: 3.8
Classifier: Development Status :: 3 - Alpha
Classifier: License :: OSI Approved :: MIT License
Classifier: Operating System :: OS Independent
Requires-Python: >=3.8.2
License-File: LICENSE
Requires-Dist: python-docx
Requires-Dist: docx2python
